LICENSE.txt
MANIFEST.in
README.rst
requirements.txt
setup.cfg
setup.py
test_requirements_py2.txt
test_requirements_py3.txt
monero/__init__.py
monero/account.py
monero/address.py
monero/base58.py
monero/block.py
monero/const.py
monero/daemon.py
monero/ed25519.py
monero/exceptions.py
monero/keccak.py
monero/numbers.py
monero/seed.py
monero/wallet.py
monero.egg-info/PKG-INFO
monero.egg-info/SOURCES.txt
monero.egg-info/dependency_links.txt
monero.egg-info/requires.txt
monero.egg-info/top_level.txt
monero/backends/__init__.py
monero/backends/offline.py
monero/backends/jsonrpc/__init__.py
monero/backends/jsonrpc/daemon.py
monero/backends/jsonrpc/exceptions.py
monero/backends/jsonrpc/wallet.py
monero/transaction/__init__.py
monero/transaction/extra.py
monero/wordlists/__init__.py
monero/wordlists/chinese_simplified.py
monero/wordlists/dutch.py
monero/wordlists/english.py
monero/wordlists/esperanto.py
monero/wordlists/french.py
monero/wordlists/german.py
monero/wordlists/italian.py
monero/wordlists/japanese.py
monero/wordlists/lojban.py
monero/wordlists/portuguese.py
monero/wordlists/russian.py
monero/wordlists/spanish.py
monero/wordlists/wordlist.py