Metadata-Version: 2.1
Name: monero
Version: 1.0.3
Summary: A comprehensive Python module for handling Monero cryptocurrency
Home-page: https://github.com/monero-ecosystem/monero-python/
Author: Michał Sałaban
Author-email: michal@salaban.info
License: BSD-3-Clause
Keywords: monero cryptocurrency
Platform: UNKNOWN
Classifier: Development Status :: 4 - Beta
Classifier: Intended Audience :: Developers
Classifier: License :: OSI Approved :: BSD License
Classifier: Operating System :: OS Independent
Classifier: Programming Language :: Python
Classifier: Programming Language :: Python :: 2.7
Classifier: Programming Language :: Python :: 3.6
Classifier: Programming Language :: Python :: 3.7
Classifier: Programming Language :: Python :: 3.8
Classifier: Programming Language :: Python :: 3.8
Classifier: Programming Language :: Python :: 3.9
Classifier: Programming Language :: Python :: 3.10
Classifier: Topic :: Software Development :: Libraries :: Python Modules
License-File: LICENSE.txt
